powerscribe/Powerscribe.py
powerscribe/__init__.py
powerscribe-1.3.dist-info/METADATA
powerscribe-1.3.dist-info/WHEEL
powerscribe-1.3.dist-info/top_level.txt
powerscribe-1.3.dist-info/RECORD
