Metadata-Version: 2.1
Name: powerscribe
Version: 1.3
Summary: A simple REST API implementation for Radiology Nuance PowerScribe 360 dictation system
Home-page: https://github.com/amin2997/PyPowerScribe
Author: Amin
Author-email: amin2997@yahoo.com
License: UNKNOWN
Platform: UNKNOWN
Classifier: Programming Language :: Python :: 3
Classifier: License :: OSI Approved :: MIT License
Classifier: Operating System :: OS Independent
Requires-Dist: requests (>=2.21.0)
